heron/.editorconfig
heron/.gitignore
heron/__init__.py
heron/cli.py
heron/condor.py
heron/detector.py
heron/filters.py
heron/inference.py
heron/injection.py
heron/likelihood.py
heron/priors.py
heron/sampling.py
heron/types.py
heron/utils.py
heron/models/__init__.py
heron/models/gpytorch.py
heron/models/lalnoise.py
heron/models/lalsimulation.py
heron/training/__init__.py
heron/training/data.py
heron/training/make-training-data.py~
heron/training/makedata.py
heron/training/makedata.py~
heron_model-0.4.0.dist-info/AUTHORS.rst
heron_model-0.4.0.dist-info/LICENSE
heron_model-0.4.0.dist-info/METADATA
heron_model-0.4.0.dist-info/WHEEL
heron_model-0.4.0.dist-info/entry_points.txt
heron_model-0.4.0.dist-info/top_level.txt
heron_model-0.4.0.dist-info/zip-safe
heron_model-0.4.0.dist-info/RECORD
