Metadata-Version: 2.1
Name: heron-model
Version: 0.4.0
Summary: Heron is a toolkit for making machine learning-based gravitational waveform models in python.
Home-page: https://github.com/transientlunatic/heron
Author: Daniel Williams
Author-email: daniel.williams@ligo.org
License: ISCL
Keywords: heron
Classifier: Development Status :: 2 - Pre-Alpha
Classifier: Intended Audience :: Developers
Classifier: License :: OSI Approved :: ISC License (ISCL)
Classifier: Natural Language :: English
Classifier: Programming Language :: Python :: 3
Classifier: Programming Language :: Python :: 3.8
Classifier: Programming Language :: Python :: 3.9
Classifier: Programming Language :: Python :: 3.10
License-File: LICENSE
License-File: AUTHORS.rst
Requires-Dist: bilby
Requires-Dist: numpy
Requires-Dist: matplotlib
Requires-Dist: scipy
Requires-Dist: progressbar
Requires-Dist: emcee
Requires-Dist: pyyaml
Requires-Dist: jinja2
Requires-Dist: cython
Requires-Dist: george
Requires-Dist: nestle
Requires-Dist: elk-waveform>=0.13
Requires-Dist: lalsuite
Requires-Dist: h5py
Requires-Dist: click
Requires-Dist: asimov
Requires-Dist: pesummary
Requires-Dist: nessai
Requires-Dist: elk-waveform
Requires-Dist: gpytorch==1.0.1
Requires-Dist: torch==2.4.0
Requires-Dist: torchvision==0.5.0
